[{"vardas":"Ania","pavarde":"Jutkevi\u010d","asmensKodas":"39404130328","saskaitosNumeris":"LT692957577387171979","likutis":211},{"vardas":"Jevg","pavarde":"Safar","asmensKodas":"39404130328","saskaitosNumeris":"LT266826307817442948","likutis":"0"},{"vardas":"obuoluys","pavarde":"asdasd","asmensKodas":"39404130328","saskaitosNumeris":"LT953489117552222398","likutis":50},{"vardas":"zeka","pavarde":"zeka","asmensKodas":"39404130328","saskaitosNumeris":"LT762561396583756572","likutis":"0"},{"vardas":"zzzz","pavarde":"zekaas","asmensKodas":"39404130328","saskaitosNumeris":"LT703950665966189397","likutis":"0"}]